freud_api_crawler/__init__.py
freud_api_crawler/entities.py
freud_api_crawler/file_utils.py
freud_api_crawler/freud_api_crawler.py
freud_api_crawler/string_utils.py
freud_api_crawler/tei_utils.py
freud_api_crawler/fixtures/make_tei.xslt
freud_api_crawler/fixtures/tei_dummy.xml
freud_api_crawler/templates/ort.xml
freud_api_crawler/templates/personen.xml
freud_api_crawler/templates/publishers.xml
freud_api_crawler/templates/tei.xml
freud_api_crawler-2.0.8.data/data/freud_api_crawler/fixtures/make_tei.xslt
freud_api_crawler-2.0.8.data/data/freud_api_crawler/fixtures/tei_dummy.xml
freud_api_crawler-2.0.8.data/data/freud_api_crawler/templates/ort.xml
freud_api_crawler-2.0.8.data/data/freud_api_crawler/templates/personen.xml
freud_api_crawler-2.0.8.data/data/freud_api_crawler/templates/publishers.xml
freud_api_crawler-2.0.8.data/data/freud_api_crawler/templates/tei.xml
freud_api_crawler-2.0.8.dist-info/LICENSE
freud_api_crawler-2.0.8.dist-info/METADATA
freud_api_crawler-2.0.8.dist-info/WHEEL
freud_api_crawler-2.0.8.dist-info/entry_points.txt
freud_api_crawler-2.0.8.dist-info/top_level.txt
freud_api_crawler-2.0.8.dist-info/RECORD
