Metadata-Version: 2.1
Name: freud-api-crawler
Version: 2.0.8
Summary: A client to interact with freud-net API
Home-page: https://github.com/acdh-oeaw/freud_api_crawler
Author: Peter Andorfer, Daniel Stoxreiter
Author-email: peter.andorfer@oeaw.ac.at
License: MIT license
Keywords: freud_api_crawler
Classifier: Development Status :: 2 - Pre-Alpha
Classifier: Intended Audience :: Developers
Classifier: License :: OSI Approved :: MIT License
Classifier: Natural Language :: English
Classifier: Programming Language :: Python :: 3.7
Classifier: Programming Language :: Python :: 3.8
Requires-Python: >=3.7
License-File: LICENSE
Requires-Dist: acdh-xml-pyutils
Requires-Dist: requests (<3,>=2.25.0)
Requires-Dist: click (>=7.1<9)
Requires-Dist: lxml (>=4.8<5)
Requires-Dist: ndjson
Requires-Dist: python-slugify (<7,>=6.0.0)
Requires-Dist: tqdm (<5,>=4.63.0)
Requires-Dist: Jinja2 (>=3.1.2)
